mergerz/__init__.py
mergerz/module.py
mergerz-4.0.3.dist-info/LICENSE
mergerz-4.0.3.dist-info/METADATA
mergerz-4.0.3.dist-info/WHEEL
mergerz-4.0.3.dist-info/top_level.txt
mergerz-4.0.3.dist-info/RECORD
