Metadata-Version: 2.2
Name: mergerz
Version: 4.0.3
Summary: Blazingly fast module to merge PDFs and slides.
Author: Afnan Tawsif
Author-email: afnantawsif778@gmail.com
License: MIT
Classifier: Programming Language :: Python :: 3
Classifier: Operating System :: OS Independent
Classifier: License :: OSI Approved :: MIT License
Requires-Python: >=3.6
License-File: LICENSE
Requires-Dist: reportlab>=4.3.1
Requires-Dist: pillow>=11.1.0
Requires-Dist: pymupdf>=1.25.3
Requires-Dist: colorama>=0.4.6
Requires-Dist: natsort>=8.4.0
Requires-Dist: pikepdf>=9.5.2
Dynamic: author
Dynamic: author-email
Dynamic: classifier
Dynamic: description
Dynamic: description-content-type
Dynamic: license
Dynamic: requires-dist
Dynamic: requires-python
Dynamic: summary
